odoo8_addon_mrp_bom_structure_xls-8.0.1.0.0-py2.7-nspkg.pth
odoo8_addon_mrp_bom_structure_xls-8.0.1.0.0.dist-info/top_level.txt
odoo8_addon_mrp_bom_structure_xls-8.0.1.0.0.dist-info/WHEEL
odoo8_addon_mrp_bom_structure_xls-8.0.1.0.0.dist-info/RECORD
odoo8_addon_mrp_bom_structure_xls-8.0.1.0.0.dist-info/metadata.json
odoo8_addon_mrp_bom_structure_xls-8.0.1.0.0.dist-info/DESCRIPTION.rst
odoo8_addon_mrp_bom_structure_xls-8.0.1.0.0.dist-info/METADATA
odoo8_addon_mrp_bom_structure_xls-8.0.1.0.0.dist-info/namespace_packages.txt
odoo_addons/mrp_bom_structure_xls/__openerp__.py
odoo_addons/mrp_bom_structure_xls/__init__.py
odoo_addons/mrp_bom_structure_xls/README.rst
odoo_addons/mrp_bom_structure_xls/report/__init__.py
odoo_addons/mrp_bom_structure_xls/report/bom_structure_xls.xml
odoo_addons/mrp_bom_structure_xls/report/bom_structure_xls.py
odoo_addons/mrp_bom_structure_xls/static/description/index.html
odoo_addons/mrp_bom_structure_xls/static/description/icon.png
